{"0":{"fields":[{"type":"text","id":14,"formId":9,"label":"Latitude","adminLabel":"","isRequired":false,"size":"large","errorMessage":"","visibility":"visible","inputs":null,"description":"","allowsPrepopulate":false,"inputMask":false,"inputMaskValue":"","inputMaskIsCustom":false,"maxLength":"","inputType":"","labelPlacement":"","descriptionPlacement":"","subLabelPlacement":"","placeholder":"","cssClass":"","inputName":"","noDuplicates":false,"defaultValue":"","enableAutocomplete":false,"autocompleteAttribute":"","choices":"","conditionalLogic":"","productField":"","layoutGridColumnSpan":6,"enablePasswordInput":"","enableEnhancedUI":0,"layoutGroupId":"ddaf9bc1","multipleFiles":false,"maxFiles":"","calculationFormula":"","calculationRounding":"","enableCalculation":"","disableQuantity":false,"displayAllCategories":false,"useRichTextEditor":false,"gk_custom_map_icon_enabled":false,"gppa-choices-filter-groups":[],"gppa-choices-templates":[],"gppa-values-filter-groups":[],"gppa-values-templates":[],"errors":[],"fields":"","displayOnly":""},{"type":"text","id":13,"formId":9,"label":"Longitude","adminLabel":"","isRequired":false,"size":"large","errorMessage":"","visibility":"visible","inputs":null,"description":"","allowsPrepopulate":false,"inputMask":false,"inputMaskValue":"","inputMaskIsCustom":false,"maxLength":"","inputType":"","labelPlacement":"","descriptionPlacement":"","subLabelPlacement":"","placeholder":"","cssClass":"","inputName":"","noDuplicates":false,"defaultValue":"","enableAutocomplete":false,"autocompleteAttribute":"","choices":"","conditionalLogic":"","productField":"","layoutGridColumnSpan":6,"enablePasswordInput":"","enableEnhancedUI":0,"layoutGroupId":"ddaf9bc1","multipleFiles":false,"maxFiles":"","calculationFormula":"","calculationRounding":"","enableCalculation":"","disableQuantity":false,"displayAllCategories":false,"useRichTextEditor":false,"gk_custom_map_icon_enabled":false,"gppa-choices-filter-groups":[],"gppa-choices-templates":[],"gppa-values-filter-groups":[],"gppa-values-templates":[],"errors":[],"fields":"","displayOnly":""},{"type":"number","id":3,"formId":9,"label":"Description","adminLabel":"","isRequired":false,"size":"large","errorMessage":"","visibility":"visible","inputs":null,"numberFormat":"decimal_dot","description":"","allowsPrepopulate":false,"inputMask":false,"inputMaskValue":"","inputMaskIsCustom":false,"maxLength":"","inputType":"","labelPlacement":"","descriptionPlacement":"","subLabelPlacement":"","placeholder":"","cssClass":"","inputName":"","noDuplicates":false,"defaultValue":"","enableAutocomplete":false,"autocompleteAttribute":"","choices":"","conditionalLogic":"","enableCalculation":false,"rangeMin":"","rangeMax":"","calculationFormula":"","productField":"","layoutGridColumnSpan":"","enableEnhancedUI":0,"layoutGroupId":"68a26faf","multipleFiles":false,"maxFiles":"","calculationRounding":"","disableQuantity":false,"displayAllCategories":false,"useRichTextEditor":false,"gk_custom_map_icon_enabled":false,"gppa-choices-filter-groups":[],"gppa-choices-templates":[],"gppa-values-filter-groups":[],"gppa-values-templates":[],"errors":[],"fields":"","displayOnly":""},{"type":"number","id":4,"formId":9,"label":"Location Status","adminLabel":"","isRequired":false,"size":"large","errorMessage":"","visibility":"visible","inputs":null,"numberFormat":"decimal_dot","description":"","allowsPrepopulate":false,"inputMask":false,"inputMaskValue":"","inputMaskIsCustom":false,"maxLength":"","inputType":"","labelPlacement":"","descriptionPlacement":"","subLabelPlacement":"","placeholder":"","cssClass":"","inputName":"","noDuplicates":false,"defaultValue":"","enableAutocomplete":false,"autocompleteAttribute":"","choices":"","conditionalLogic":"","enableCalculation":false,"rangeMin":"","rangeMax":"","calculationFormula":"","productField":"","layoutGridColumnSpan":"","enableEnhancedUI":0,"layoutGroupId":"7d078648","multipleFiles":false,"maxFiles":"","calculationRounding":"","disableQuantity":false,"displayAllCategories":false,"useRichTextEditor":false,"gk_custom_map_icon_enabled":false,"gppa-choices-filter-groups":[],"gppa-choices-templates":[],"gppa-values-filter-groups":[],"gppa-values-templates":[],"errors":[],"fields":"","displayOnly":""},{"type":"select","id":7,"formId":9,"label":"Client","adminLabel":"","isRequired":false,"size":"large","errorMessage":"","visibility":"visible","validateState":true,"inputs":null,"choices":[{"text":"Csu Electric","value":"Csu Electric","isSelected":false,"price":""},{"text":"Csu Gas","value":"Csu Gas","isSelected":false,"price":""},{"text":"Csu","value":"Csu","isSelected":false,"price":""},{"text":"Sefnco","value":"Sefnco","isSelected":false,"price":""},{"text":"Tilson","value":"Tilson","isSelected":false,"price":""},{"text":"C&amp;b","value":"C&b","isSelected":false,"price":""},{"text":"Main Electric","value":"Main Electric","isSelected":false,"price":""},{"text":"Maers","value":"Maers","isSelected":false,"price":""}],"description":"","allowsPrepopulate":false,"inputMask":false,"inputMaskValue":"","inputMaskIsCustom":false,"maxLength":"","inputType":"","labelPlacement":"","descriptionPlacement":"","subLabelPlacement":"","placeholder":"","cssClass":"","inputName":"","noDuplicates":false,"defaultValue":"","enableAutocomplete":false,"autocompleteAttribute":"","conditionalLogic":"","productField":"","layoutGridColumnSpan":12,"enablePrice":"","enableEnhancedUI":0,"layoutGroupId":"4a16ff47","multipleFiles":false,"maxFiles":"","calculationFormula":"","calculationRounding":"","enableCalculation":"","disableQuantity":false,"displayAllCategories":false,"useRichTextEditor":false,"gk_custom_map_icon_enabled":false,"gppa-choices-filter-groups":[],"gppa-choices-templates":[],"gppa-values-filter-groups":[],"gppa-values-templates":[],"errors":[],"fields":"","displayOnly":""},{"type":"select","id":6,"formId":9,"label":"Type","adminLabel":"","isRequired":false,"size":"large","errorMessage":"","visibility":"visible","validateState":true,"inputs":null,"choices":[{"text":"Road","value":"Road","isSelected":false,"price":""},{"text":"Curv","value":"Curv","isSelected":false,"price":""},{"text":"Sidewalk","value":"Sidewalk","isSelected":false,"price":""},{"text":"Driveway","value":"Driveway","isSelected":false,"price":""},{"text":"Offroad","value":"Offroad","isSelected":false,"price":""}],"description":"","allowsPrepopulate":false,"inputMask":false,"inputMaskValue":"","inputMaskIsCustom":false,"maxLength":"","inputType":"","labelPlacement":"","descriptionPlacement":"","subLabelPlacement":"","placeholder":"","cssClass":"","inputName":"","noDuplicates":false,"defaultValue":"","enableAutocomplete":false,"autocompleteAttribute":"","conditionalLogic":"","productField":"","layoutGridColumnSpan":"","enablePrice":"","enableEnhancedUI":0,"layoutGroupId":"c9d771e8","multipleFiles":false,"maxFiles":"","calculationFormula":"","calculationRounding":"","enableCalculation":"","disableQuantity":false,"displayAllCategories":false,"useRichTextEditor":false,"gk_custom_map_icon_enabled":false,"gppa-choices-filter-groups":[],"gppa-choices-templates":[],"gppa-values-filter-groups":[],"gppa-values-templates":[],"errors":[],"fields":"","displayOnly":""},{"type":"text","id":8,"formId":9,"label":"Noty","adminLabel":"","isRequired":false,"size":"large","errorMessage":"","visibility":"visible","inputs":null,"description":"","allowsPrepopulate":false,"inputMask":false,"inputMaskValue":"","inputMaskIsCustom":false,"maxLength":"","inputType":"","labelPlacement":"","descriptionPlacement":"","subLabelPlacement":"","placeholder":"","cssClass":"","inputName":"","noDuplicates":false,"defaultValue":"","enableAutocomplete":false,"autocompleteAttribute":"","choices":"","conditionalLogic":"","productField":"","layoutGridColumnSpan":"","enablePasswordInput":"","enableEnhancedUI":0,"layoutGroupId":"8ed037c2","multipleFiles":false,"maxFiles":"","calculationFormula":"","calculationRounding":"","enableCalculation":"","disableQuantity":false,"displayAllCategories":false,"useRichTextEditor":false,"gk_custom_map_icon_enabled":false,"gppa-choices-filter-groups":[],"gppa-choices-templates":[],"gppa-values-filter-groups":[],"gppa-values-templates":[],"errors":[],"fields":"","displayOnly":""},{"type":"name","id":9,"formId":9,"label":"Set By","adminLabel":"","isRequired":false,"size":"large","errorMessage":"","visibility":"hidden","nameFormat":"advanced","inputs":[{"id":"9.2","label":"Prefix","name":"","autocompleteAttribute":"honorific-prefix","choices":[{"text":"Dr.","value":"Dr."},{"text":"Miss","value":"Miss"},{"text":"Mr.","value":"Mr."},{"text":"Mrs.","value":"Mrs."},{"text":"Ms.","value":"Ms."},{"text":"Mx.","value":"Mx."},{"text":"Prof.","value":"Prof."},{"text":"Rev.","value":"Rev."}],"isHidden":true,"inputType":"radio"},{"id":"9.3","label":"First","name":"","autocompleteAttribute":"given-name","defaultValue":"{user:first_name}"},{"id":"9.4","label":"Middle","name":"","autocompleteAttribute":"additional-name","isHidden":true},{"id":"9.6","label":"Last","name":"","autocompleteAttribute":"family-name","defaultValue":"{user:last_name}"},{"id":"9.8","label":"Suffix","name":"","autocompleteAttribute":"honorific-suffix","isHidden":true}],"description":"","allowsPrepopulate":false,"inputMask":false,"inputMaskValue":"","inputMaskIsCustom":false,"maxLength":"","inputType":"","labelPlacement":"","descriptionPlacement":"","subLabelPlacement":"","placeholder":"","cssClass":"","inputName":"","noDuplicates":false,"defaultValue":"","enableAutocomplete":true,"autocompleteAttribute":"","choices":"","conditionalLogic":"","productField":"","layoutGridColumnSpan":"","enableEnhancedUI":0,"layoutGroupId":"603da499","multipleFiles":false,"maxFiles":"","calculationFormula":"","calculationRounding":"","enableCalculation":"","disableQuantity":false,"displayAllCategories":false,"useRichTextEditor":false,"gk_custom_map_icon_enabled":false,"gppa-choices-filter-groups":[],"gppa-choices-templates":[],"gppa-values-filter-groups":[],"gppa-values-templates":[],"errors":[],"fields":"","displayOnly":""},{"type":"date","id":10,"formId":9,"label":"Date Set","adminLabel":"","isRequired":false,"size":"large","errorMessage":"","visibility":"visible","inputs":null,"dateType":"datepicker","dateFormat":"mdy","dateFormatPlacement":"below","calendarIconType":"none","description":"","allowsPrepopulate":false,"inputMask":false,"inputMaskValue":"","inputMaskIsCustom":false,"maxLength":"","inputType":"","labelPlacement":"","descriptionPlacement":"","subLabelPlacement":"","placeholder":"{date_mdy}","cssClass":"","inputName":"","noDuplicates":false,"defaultValue":"","enableAutocomplete":false,"autocompleteAttribute":"","choices":"","conditionalLogic":"","calendarIconUrl":"","productField":"","layoutGridColumnSpan":6,"enableEnhancedUI":0,"layoutGroupId":"c62dbb6c","multipleFiles":false,"maxFiles":"","calculationFormula":"","calculationRounding":"","enableCalculation":"","disableQuantity":false,"displayAllCategories":false,"useRichTextEditor":false,"gk_custom_map_icon_enabled":false,"gppa-choices-filter-groups":[],"gppa-choices-templates":[],"gppa-values-filter-groups":[],"gppa-values-templates":[],"errors":[],"fields":"","displayOnly":""},{"type":"text","id":12,"formId":9,"label":"Time Set","adminLabel":"","isRequired":false,"size":"large","errorMessage":"","visibility":"hidden","inputs":null,"description":"","allowsPrepopulate":false,"inputMask":false,"inputMaskValue":"","inputMaskIsCustom":false,"maxLength":"","inputType":"","labelPlacement":"","descriptionPlacement":"","subLabelPlacement":"","placeholder":"{current_time}","cssClass":"","inputName":"","noDuplicates":false,"defaultValue":"{current_time}","enableAutocomplete":false,"autocompleteAttribute":"","choices":"","conditionalLogic":"","productField":"","layoutGridColumnSpan":6,"enablePasswordInput":"","enableEnhancedUI":0,"layoutGroupId":"c62dbb6c","multipleFiles":false,"maxFiles":"","calculationFormula":"","calculationRounding":"","enableCalculation":"","disableQuantity":false,"displayAllCategories":false,"useRichTextEditor":false,"gk_custom_map_icon_enabled":false,"gppa-choices-filter-groups":[],"gppa-choices-templates":[],"gppa-values-filter-groups":[],"gppa-values-templates":[],"errors":[],"fields":"","displayOnly":""},{"type":"date","id":15,"formId":9,"label":"Date Collected","adminLabel":"","isRequired":false,"size":"large","errorMessage":"","visibility":"visible","inputs":null,"dateType":"datepicker","dateFormat":"mdy","dateFormatPlacement":"below","calendarIconType":"none","description":"","allowsPrepopulate":false,"inputMask":false,"inputMaskValue":"","inputMaskIsCustom":false,"maxLength":"","inputType":"","labelPlacement":"","descriptionPlacement":"","subLabelPlacement":"","placeholder":"","cssClass":"","inputName":"","noDuplicates":false,"defaultValue":"","enableAutocomplete":false,"autocompleteAttribute":"","choices":"","conditionalLogic":"","calendarIconUrl":"","productField":"","layoutGridColumnSpan":6,"enableEnhancedUI":0,"layoutGroupId":"6e1adeb2","multipleFiles":false,"maxFiles":"","calculationFormula":"","calculationRounding":"","enableCalculation":"","disableQuantity":false,"displayAllCategories":false,"useRichTextEditor":false,"gk_custom_map_icon_enabled":false,"gppa-choices-filter-groups":[],"gppa-choices-templates":[],"gppa-values-filter-groups":[],"gppa-values-templates":[],"errors":[],"fields":"","displayOnly":""},{"type":"time","id":17,"formId":9,"label":"Time Collected","adminLabel":"","isRequired":false,"size":"large","errorMessage":"","visibility":"visible","inputs":[{"id":"17.1","label":"Hour","name":""},{"id":"17.2","label":"Minute","name":""},{"id":"17.3","label":"AM\/PM","name":""}],"description":"","allowsPrepopulate":false,"inputMask":false,"inputMaskValue":"","inputMaskIsCustom":false,"maxLength":"","inputType":"","labelPlacement":"","descriptionPlacement":"","subLabelPlacement":"","placeholder":"","cssClass":"","inputName":"","noDuplicates":false,"defaultValue":"","enableAutocomplete":false,"autocompleteAttribute":"","choices":"","conditionalLogic":"","timeFormat":"12","productField":"","layoutGridColumnSpan":6,"enableEnhancedUI":0,"layoutGroupId":"6e1adeb2","multipleFiles":false,"maxFiles":"","calculationFormula":"","calculationRounding":"","enableCalculation":"","disableQuantity":false,"displayAllCategories":false,"useRichTextEditor":false,"gk_custom_map_icon_enabled":false,"gppa-choices-filter-groups":[],"gppa-choices-templates":[],"gppa-values-filter-groups":[],"gppa-values-templates":[],"errors":[],"fields":"","displayOnly":""},{"type":"select","id":18,"label":"Location Status","visibility":"visible","formId":9,"fields":"","cssClass":"","displayOnly":"","isRequired":false,"inputs":"","layoutGroupId":"1659e9df","adminLabel":"","description":"","allowsPrepopulate":false,"inputMask":false,"inputMaskValue":"","inputMaskIsCustom":"","maxLength":"","inputType":"","errorMessage":"","labelPlacement":"","descriptionPlacement":"","subLabelPlacement":"","placeholder":"","inputName":"","noDuplicates":false,"defaultValue":"","enableAutocomplete":false,"autocompleteAttribute":"","choices":"","conditionalLogic":""},{"type":"text","id":19,"label":"Set By","visibility":"visible","formId":9,"fields":"","cssClass":"","displayOnly":"","isRequired":false,"inputs":"","layoutGroupId":"97f1bd28","adminLabel":"","description":"","allowsPrepopulate":false,"inputMask":false,"inputMaskValue":"","inputMaskIsCustom":"","maxLength":"","inputType":"","errorMessage":"","labelPlacement":"","descriptionPlacement":"","subLabelPlacement":"","placeholder":"","inputName":"","noDuplicates":false,"defaultValue":"","enableAutocomplete":false,"autocompleteAttribute":"","choices":"","conditionalLogic":""},{"type":"number","id":20,"label":"ID","visibility":"visible","formId":9,"fields":"","cssClass":"","displayOnly":"","isRequired":false,"inputs":"","layoutGroupId":"576696f2","adminLabel":"","description":"","allowsPrepopulate":false,"inputMask":false,"inputMaskValue":"","inputMaskIsCustom":"","maxLength":"","inputType":"","errorMessage":"","labelPlacement":"","descriptionPlacement":"","subLabelPlacement":"","placeholder":"","inputName":"","noDuplicates":false,"defaultValue":"","enableAutocomplete":false,"autocompleteAttribute":"","choices":"","conditionalLogic":"","enableCalculation":false,"numberFormat":"decimal_dot","rangeMin":"","rangeMax":""}],"button":{"type":"text","text":"","imageUrl":"","width":"auto","location":"bottom","layoutGridColumnSpan":12},"title":"Pothole Covers","description":"","version":"2.7.6","id":9,"markupVersion":2,"nextFieldId":21,"useCurrentUserAsAuthor":true,"postContentTemplateEnabled":false,"postTitleTemplateEnabled":false,"postTitleTemplate":"","postContentTemplate":"","lastPageButton":null,"pagination":null,"firstPageCssClass":null,"is_active":"1","date_created":"2023-05-13 01:20:19","is_trash":"0","confirmations":[{"id":"645ee5d3705e4","name":"Default Confirmation","isDefault":true,"type":"message","message":"Thanks for contacting us! We will get in touch with you shortly.","url":"","pageId":"","queryString":""}],"notifications":[{"id":"645ee5d37045d","isActive":true,"to":"{admin_email}","name":"Admin Notification","event":"form_submission","toType":"email","subject":"New submission from {form_title}","message":"{all_fields}"}]},"version":"2.7.6"}